{"node":{"0045e610bb9245feea0d957a234293cbdc4ba056c0":{"workers":{"app/page":{"moduleId":"14253","async":false},"app/create/page":{"moduleId":"16403","async":false}},"layer":{"app/page":"rsc","app/create/page":"action-browser"}},"60abd550f7bbc941c95a6f68fd010c6d322b825d95":{"workers":{"app/page":{"moduleId":"14253","async":false},"app/create/page":{"moduleId":"16403","async":false}},"layer":{"app/page":"rsc","app/create/page":"action-browser"}}},"edge":{},"encryptionKey":"fgTPAWo3Mw+IjXFlXcLNlHEkG6P1QefWQS2C8iX1tHI="}